StoRecognition/LoginForm.py
StoRecognition/LoginWindow.py
StoRecognition/RecSystem.py
StoRecognition/Recognition_UI.py
StoRecognition/System_login.py
StoRecognition/System_noLogin.py
StoRecognition/TEST.py
StoRecognition/YOLOv8v5Model.py
StoRecognition/__init__.py
StoRecognition/run_main_login.py
StoRecognition/run_main_noLogin.py
StoRecognition/run_test_camera.py
StoRecognition/run_test_image.py
StoRecognition/run_test_video.py
StoRecognition/run_train_model.py
StoRecognition-1.0.0.dist-info/METADATA
StoRecognition-1.0.0.dist-info/WHEEL
StoRecognition-1.0.0.dist-info/entry_points.txt
StoRecognition-1.0.0.dist-info/top_level.txt
StoRecognition-1.0.0.dist-info/RECORD
