Metadata-Version: 2.1
Name: StoRecognition
Version: 1.0.0
Summary: 基于YOLOv8植物叶表气孔识别项目
Author: gdf
Author-email: 1304245067@qq.com
Requires-Dist: absl-py==2.0.0
Requires-Dist: addict==2.4.0
Requires-Dist: cachetools==4.2.4
Requires-Dist: captcha==0.4
Requires-Dist: certifi==2023.5.7
Requires-Dist: charset-normalizer==3.1.0
Requires-Dist: colorama==0.4.6
Requires-Dist: coloredlogs==15.0.1
Requires-Dist: contourpy==1.1.0
Requires-Dist: cycler==0.11.0
Requires-Dist: filelock==3.12.2
Requires-Dist: flatbuffers==23.5.26
Requires-Dist: fonttools==4.40.0
Requires-Dist: google-auth==2.25.2
Requires-Dist: google-auth-oauthlib==1.2.0
Requires-Dist: grpcio==1.60.0
Requires-Dist: humanfriendly==10.0
Requires-Dist: idna==3.4
Requires-Dist: IMcore==0.2.7
Requires-Dist: Jinja2==3.1.2
Requires-Dist: kiwisolver==1.4.4
Requires-Dist: Markdown==3.5.1
Requires-Dist: MarkupSafe==2.1.3
Requires-Dist: matplotlib==3.7.1
Requires-Dist: mpmath==1.3.0
Requires-Dist: networkx==3.1
Requires-Dist: numpy==1.24.3
Requires-Dist: oauthlib==3.2.2
Requires-Dist: onnxruntime==1.15.0
Requires-Dist: opencv-python==4.7.0.72
Requires-Dist: packaging==23.1
Requires-Dist: pandas==2.0.2
Requires-Dist: Pillow==9.5.0
Requires-Dist: protobuf==4.23.4
Requires-Dist: psutil==5.9.5
Requires-Dist: py-cpuinfo==9.0.0
Requires-Dist: pyasn1==0.5.1
Requires-Dist: pyasn1-modules==0.3.0
Requires-Dist: pycocotools==2.0.7
Requires-Dist: pyparsing==3.0.9
Requires-Dist: pyreadline3==3.4.1
Requires-Dist: PySide6==6.5.1.1
Requires-Dist: PySide6-Addons==6.5.1.1
Requires-Dist: PySide6-Essentials==6.5.1.1
Requires-Dist: python-dateutil==2.8.2
Requires-Dist: pytz==2023.3
Requires-Dist: PyYAML==6.0
Requires-Dist: QtFusion==0.5.4
Requires-Dist: requests==2.31.0
Requires-Dist: requests-oauthlib==1.3.1
Requires-Dist: rsa==4.9
Requires-Dist: scipy==1.10.1
Requires-Dist: seaborn==0.12.2
Requires-Dist: shiboken6==6.5.1.1
Requires-Dist: six==1.16.0
Requires-Dist: sympy==1.12
Requires-Dist: tensorboard==2.15.1
Requires-Dist: tensorboard-data-server==0.7.2
Requires-Dist: tensorboard-plugin-wit==1.8.1
Requires-Dist: thop==0.1.1.post2209072238
Requires-Dist: torch==2.0.1
Requires-Dist: torchvision==0.15.2
Requires-Dist: tqdm==4.65.0
Requires-Dist: typing-extensions==4.6.3
Requires-Dist: tzdata==2023.3
Requires-Dist: urllib3==2.0.3
Requires-Dist: Werkzeug==3.0.1
